main.py
wayspiritmcp_weather-0.8.0.dist-info/METADATA
wayspiritmcp_weather-0.8.0.dist-info/WHEEL
wayspiritmcp_weather-0.8.0.dist-info/entry_points.txt
wayspiritmcp_weather-0.8.0.dist-info/top_level.txt
wayspiritmcp_weather-0.8.0.dist-info/RECORD
