Metadata-Version: 2.4
Name: wayspiritmcp-weather
Version: 0.8.0
Summary: MCP attack test for weather
Requires-Python: >=3.10
Requires-Dist: httpx>=0.28.1
Requires-Dist: mcp>=1.12.2
